README.rst
setup.py
unchain/__init__.py
unchain/__main__.py
unchain.egg-info/PKG-INFO
unchain.egg-info/SOURCES.txt
unchain.egg-info/dependency_links.txt
unchain.egg-info/entry_points.txt
unchain.egg-info/requires.txt
unchain.egg-info/top_level.txt