Metadata-Version: 1.1
Name: unchain
Version: 0.1
Summary: Websocket companion for Django
Home-page: https://github.com/hoh/Unchain/
Author: Hugo Herter
Author-email: @hugoherter.com
License: AGPLv3
Keywords: websocket django publish subscribe
Platform: UNKNOWN
Classifier: Development Status :: 3 - Alpha
Classifier: Environment :: Console
Classifier: Programming Language :: Python :: 3
Classifier: Intended Audience :: Developers
Classifier: Intended Audience :: Information Technology
Classifier: Natural Language :: English
Classifier: Operating System :: POSIX :: Linux
Classifier: License :: OSI Approved :: GNU Affero General Public License v3
Classifier: Topic :: Internet :: WWW/HTTP
